pytest_assert_type/__init__.py
pytest_assert_type/plugin.py
pytest_assert_type/py.typed
pytest_assert_type/subtests_pycharm_patch.py
pytest_assert_type-0.1.3.dist-info/WHEEL
pytest_assert_type-0.1.3.dist-info/entry_points.txt
pytest_assert_type-0.1.3.dist-info/METADATA
pytest_assert_type-0.1.3.dist-info/RECORD
