Metadata-Version: 2.3
Name: pytest-assert-type
Version: 0.1.3
Summary: Use typing.assert_type() to test runtime behavior
Keywords: pytest,plugin,subtests,typing,pydantic,assert_type
Author: Arseny Boykov (Bobronium)
Author-email: Arseny Boykov (Bobronium) <hi@bobronium.me>
License: MIT
Classifier: Framework :: Pytest
Classifier: Programming Language :: Python :: 3
Classifier: Programming Language :: Python :: 3 :: Only
Classifier: Programming Language :: Python :: 3.11
Classifier: Programming Language :: Python :: 3.12
Classifier: License :: OSI Approved :: MIT License
Classifier: Development Status :: 3 - Alpha
Classifier: Intended Audience :: Developers
Classifier: Topic :: Software Development :: Testing
Requires-Dist: pytest>=6.2.0
Requires-Dist: pytest-subtests>=0.4
Requires-Dist: pydantic>=2.0
Requires-Dist: typing-extensions>=4.8 ; python_full_version < '3.12'
Requires-Dist: pytest-assert-type[lint] ; extra == 'dev'
Requires-Dist: pytest-assert-type[typecheck] ; extra == 'dev'
Requires-Dist: pytest-assert-type[test] ; extra == 'dev'
Requires-Dist: ruff>=0.1.9 ; extra == 'lint'
Requires-Dist: typing-extensions ; extra == 'test'
Requires-Dist: pytest>=6.2.5 ; extra == 'test'
Requires-Dist: pytest-cov>=7.0.0 ; extra == 'test'
Requires-Dist: coverage>=7.10.7 ; extra == 'test'
Requires-Dist: mypy>=1.18.2 ; extra == 'typecheck'
Requires-Dist: pyright>=1.1.406 ; extra == 'typecheck'
Requires-Dist: zuban>=0.1.0 ; extra == 'typecheck'
Requires-Dist: pluggy>=1.0 ; extra == 'typecheck'
Requires-Python: >=3.10
Project-URL: Homepage, https://github.com/Bobronium/pytest-assert-type
Project-URL: Issues, https://github.com/Bobronium/pytest-assert-type/issues
Project-URL: Source, https://github.com/Bobronium/pytest-assert-type
Provides-Extra: dev
Provides-Extra: lint
Provides-Extra: test
Provides-Extra: typecheck
